LICENSE
README.md
setup.cfg
setup.py
boardgamegeek/__init__.py
boardgamegeek/api.py
boardgamegeek/cache.py
boardgamegeek/exceptions.py
boardgamegeek/legacy_api.py
boardgamegeek/main.py
boardgamegeek/utils.py
boardgamegeek/version.py
boardgamegeek/loaders/__init__.py
boardgamegeek/loaders/collection.py
boardgamegeek/loaders/game.py
boardgamegeek/loaders/geeklist.py
boardgamegeek/loaders/guild.py
boardgamegeek/loaders/hotitems.py
boardgamegeek/loaders/plays.py
boardgamegeek/objects/__init__.py
boardgamegeek/objects/collection.py
boardgamegeek/objects/games.py
boardgamegeek/objects/geeklist.py
boardgamegeek/objects/guild.py
boardgamegeek/objects/hotitems.py
boardgamegeek/objects/plays.py
boardgamegeek/objects/search.py
boardgamegeek/objects/things.py
boardgamegeek/objects/user.py
python_boardgamegeek.egg-info/PKG-INFO
python_boardgamegeek.egg-info/SOURCES.txt
python_boardgamegeek.egg-info/dependency_links.txt
python_boardgamegeek.egg-info/entry_points.txt
python_boardgamegeek.egg-info/requires.txt
python_boardgamegeek.egg-info/top_level.txt
test/test_collection.py
test/test_game.py
test/test_geeklist.py
test/test_guild.py
test/test_hot_items.py
test/test_loaders_collection.py
test/test_misc.py
test/test_plays.py
test/test_search.py
test/test_user.py
test/test_utils.py