Metadata-Version: 2.1
Name: python-boardgamegeek
Version: 1.1.0
Summary: A Python interface to boardgamegeek.com's API
Home-page: https://github.com/mmonkey/boardgamegeek
Author: CJ O'Hara
Author-email: mmonkey@gmail.com
License: BSD
Platform: UNKNOWN
Classifier: Programming Language :: Python :: 2.7
Classifier: Programming Language :: Python :: 3.8
Classifier: Programming Language :: Python :: 3.9
Classifier: License :: OSI Approved :: BSD License
Classifier: Development Status :: 4 - Beta
Classifier: Operating System :: OS Independent
Classifier: Intended Audience :: Developers
Classifier: Topic :: Games/Entertainment :: Board Games
Classifier: Topic :: Internet :: WWW/HTTP :: Dynamic Content
Provides-Extra: test
License-File: LICENSE
